 {
	"info": {
		"_postman_id": "d0cc07e5-9542-47cc-9ad7-2764944a0cc0",
		"name": "santander",
		"schema": "https://schema.getpostman.com/json/collection/v2.1.0/collection.json"
	},
	"item": [
		{
			"name": "getalltran",
			"request": {
				"method": "GET",
				"header": [],
				"url": {
					"raw": "http://localhost:8080/api/transactions",
					"protocol": "http",
					"host": [
						"localhost"
					],
					"port": "8080",
					"path": [
						"api",
						"transactions"
					]
				}
			},
			"response": []
		},
		{
			"name": "getalltranbysender",
			"request": {
				"method": "GET",
				"header": [],
				"url": {
					"raw": "http://localhost:8080/api/transactions/123",
					"protocol": "http",
					"host": [
						"localhost"
					],
					"port": "8080",
					"path": [
						"api",
						"transactions",
						"123"
					]
				}
			},
			"response": []
		},
		{
			"name": "excutetran",
			"request": {
				"method": "POST",
				"header": [],
				"body": {
					"mode": "raw",
					"raw": "{\r\n    \"sender\":\"\",\r\n    \"receiver\":\"\",\r\n    \"amount\":\"\"\r\n}",
					"options": {
						"raw": {
							"language": "json"
						}
					}
				},
				"url": {
					"raw": "http://localhost:8080/api/transaction",
					"protocol": "http",
					"host": [
						"localhost"
					],
					"port": "8080",
					"path": [
						"api",
						"transaction"
					]
				}
			},
			"response": []
		}
	]
}